proxyChecker.py
proxyScraper.py
proxyz-0.2.0.dist-info/LICENSE
proxyz-0.2.0.dist-info/METADATA
proxyz-0.2.0.dist-info/WHEEL
proxyz-0.2.0.dist-info/entry_points.txt
proxyz-0.2.0.dist-info/top_level.txt
proxyz-0.2.0.dist-info/RECORD
