Metadata-Version: 2.1
Name: proxyz
Version: 0.2.0
Summary: scrape proxies from more than 5 different sources and check which ones are still alive
Home-page: https://github.com/iw4p/proxy-scraper
Author: Nima Akbarzadeh
Author-email: iw4p@protonmail.com
Classifier: Programming Language :: Python :: 3
Classifier: License :: OSI Approved :: MIT License
Classifier: Operating System :: OS Independent
Requires-Python: >=3.7
License-File: LICENSE
Requires-Dist: httpx
Requires-Dist: beautifulsoup4
Requires-Dist: pysocks
